MANIFEST.in
README.md
pyproject.toml
setup.py
cpp/cic.cpp
cpp/cpp_kernels.cpp
cpp/cpp_kernels.hpp
cpp/cubic.cpp
cpp/estimate_power_spectrum.cpp
cpp/interpolation_args.hpp
cpp/kbin_average.cpp
cpp/multiply_xli.cpp
kszx/BoundingBox.py
kszx/Box.py
kszx/Catalog.py
kszx/CmbClFitter.py
kszx/Cosmology.py
kszx/KszPipe.py
kszx/PgvLikelihood.py
kszx/RegulatedDeconvolver.py
kszx/SurrogateFactory.py
kszx/__init__.py
kszx/__main__.py
kszx/act.py
kszx/core.py
kszx/desi.py
kszx/desils_lrg.py
kszx/desils_main.py
kszx/healpix_utils.py
kszx/io_utils.py
kszx/mlhack.py
kszx/pixell_utils.py
kszx/planck.py
kszx/plot.py
kszx/sdss.py
kszx/utils.py
kszx/wfunc_utils.py
kszx.egg-info/PKG-INFO
kszx.egg-info/SOURCES.txt
kszx.egg-info/dependency_links.txt
kszx.egg-info/not-zip-safe
kszx.egg-info/requires.txt
kszx.egg-info/top_level.txt
kszx/retirement_home/RichardsonLucyDeconvolver.py
kszx/retirement_home/__init__.py
kszx/tests/__init__.py
kszx/tests/helpers.py
kszx/tests/test_box.py
kszx/tests/test_fft.py
kszx/tests/test_lss.py
kszx/tests/test_mlhack.py
kszx/tests/test_utils.py
kszx/timing/__init__.py
kszx/timing/time_interpolation.py
kszx/timing/time_multiply_xli.py