Metadata-Version: 2.4
Name: kszx
Version: 0.0.15
Requires-Python: >=3.11
Requires-Dist: scipy
Requires-Dist: matplotlib
Requires-Dist: h5py
Requires-Dist: wget
Requires-Dist: astropy
Requires-Dist: camb
Requires-Dist: healpy
Requires-Dist: fitsio
Requires-Dist: pixell
Requires-Dist: numba
Dynamic: requires-python
